pairplots/__init__.py
pairplots/__main__.py
pairplots/julia_helpers.py
pairplots/julia_import.py
pairplots/juliapkg.json
pairplots/python_interface.py
pairplots/version.py
pairplots-0.0.3.dist-info/LICENSE
pairplots-0.0.3.dist-info/METADATA
pairplots-0.0.3.dist-info/WHEEL
pairplots-0.0.3.dist-info/top_level.txt
pairplots-0.0.3.dist-info/RECORD
