Metadata-Version: 2.1
Name: pairplots
Version: 0.0.3
Summary: Beautiful and flexible visualizations of high dimensional data
Author-email: William Thompson <will.thompson@outlook.com>
License: MIT License
Classifier: Programming Language :: Python :: 3
Classifier: Operating System :: OS Independent
Classifier: License :: OSI Approved :: Apache Software License
Requires-Python: >=3.8
License-File: LICENSE
Requires-Dist: pandas <3.0.0,>=0.21.0
Requires-Dist: numpy <2.0.0,>=1.13.0
Requires-Dist: juliacall ==0.9.19
Requires-Dist: setuptools >=50.0.0
